match_video/__init__.py
match_video/anchor.py
match_video/cli.py
match_video/utils.py
match_video-0.1.5.dist-info/LICENSE
match_video-0.1.5.dist-info/METADATA
match_video-0.1.5.dist-info/WHEEL
match_video-0.1.5.dist-info/entry_points.txt
match_video-0.1.5.dist-info/RECORD
