Metadata-Version: 2.1
Name: match-video
Version: 0.1.5
Summary: A Python library that simplifies working with video from soccer matches.
Home-page: https://gitlab.com/grantwenzinger/match-video
Keywords: soccer,football,match,video
Author: Grant Wenzinger
Author-email: grantwenzinger@gmail.com
Requires-Python: >=3.9.0,<4.0.0
Classifier: Programming Language :: Python :: 3
Classifier: Programming Language :: Python :: 3.9
Classifier: Programming Language :: Python :: 3.10
Classifier: Programming Language :: Python :: 3.11
Provides-Extra: examples
Provides-Extra: lint
Provides-Extra: test
Requires-Dist: black (>=22.3.0,<23.0.0) ; extra == "lint"
Requires-Dist: coverage[toml] (>=6.4,<7.0) ; extra == "test"
Requires-Dist: flake8 (>=4.0.1,<5.0.0) ; extra == "lint"
Requires-Dist: isort (>=5.6.4,<6.0.0) ; extra == "lint"
Requires-Dist: jupyterlab (>=3.6.1,<4.0.0) ; extra == "examples"
Requires-Dist: numpy (==1.23.4) ; extra == "examples"
Requires-Dist: pre-commit (>=2.19.0,<3.0.0) ; extra == "lint"
Requires-Dist: pyarrow (==10.0.0) ; extra == "examples"
Requires-Dist: pytest (>=7.1.2,<8.0.0) ; extra == "test"
Requires-Dist: pytest-cov (>=3.0.0,<4.0.0) ; extra == "test"
Requires-Dist: pytest-mock (>=3.2.0,<4.0.0) ; extra == "test"
Requires-Dist: pytest-sugar (>=0.9.4,<0.10.0) ; extra == "test"
Requires-Dist: streamlit (>=1.12.0,<2.0.0) ; extra == "examples"
Requires-Dist: typer[all] (>=0.12.3,<0.13.0)
Requires-Dist: xmltodict (>=0.13.0,<0.14.0) ; extra == "examples"
Project-URL: Repository, https://gitlab.com/grantwenzinger/match-video
